bln_tools-0.0.2.data/scripts/harmonize
bln_tools-0.0.2.data/scripts/harmonizer
bln_tools-0.0.2.data/scripts/labeler
harmonizer/__init__.py
harmonizer/harmonizer.py
labeler/__init__.py
labeler/labeler.py
power-bi/__init__.py
power-bi/scrape.py
bln_tools-0.0.2.dist-info/LICENSE
bln_tools-0.0.2.dist-info/METADATA
bln_tools-0.0.2.dist-info/WHEEL
bln_tools-0.0.2.dist-info/top_level.txt
bln_tools-0.0.2.dist-info/RECORD
