Metadata-Version: 2.1
Name: bln-tools
Version: 0.0.2
Summary: Big Local News Tools
Home-page: https://github.com/biglocalnews/tools
Author: Daniel Jenson
Author-email: djenson@stanford.edu
License: GNU GPLv3
Platform: UNKNOWN
Classifier: Programming Language :: Python :: 3
Classifier: License :: OSI Approved :: GNU General Public License v3 (GPLv3)
Classifier: Operating System :: OS Independent
Requires-Python: >=3.6
License-File: LICENSE
Requires-Dist: fuzzywuzzy
Requires-Dist: numpy
Requires-Dist: pandas
Requires-Dist: python-Levenshtein
Requires-Dist: questionary
Requires-Dist: sklearn
